{
	"pages": [
		{
			"path": "pages/index/index",
			"style": {
				"navigationBarTitleText": "首页"
			}
		},
		{
			"path": "pages/detail/detail",
			"style": {
				"navigationBarTitleText": ""
			}
		},
		{
			"path": "pages/analysis/analysis",
			"style": {
				"navigationBarTitleText": ""
			}
		},
		{
			"path": "pages/input/input",
			"style": {
				"navigationBarTitleText": ""
			}
		},
		{
			"path": "pages/yearTable/yearTable",
			"style": {
				"navigationBarTitleText": ""
			}
		}
	],
	"globalStyle": {
		"navigationBarTextStyle": "black",
		"navigationBarTitleText": "DataAnalysis",
		"navigationBarBackgroundColor": "#F8F8F8",
		"backgroundColor": "#F8F8F8"
	},
	"uniIdRouter": {}
}