{
	"pages": [
		{
			"path": "pages/index/index",
			"style": {
				"navigationBarTitleText": "首页"
			}
		},
		 {
		  "path": "uni_modules/uni-upgrade-center-app/pages/upgrade-popup",
		  "style": {
		    "disableScroll": true,
		    "app-plus": {
		      "backgroundColorTop": "transparent",
		      "background": "transparent",
		      "titleNView": false,
		      "scrollIndicator": false,
		      "popGesture": "none",
		      "animationType": "fade-in",
		      "animationDuration": 200
		    }
		  }
		},
		{
			"path": "pages/detail/detail",
			"style": {
				"navigationBarTitleText": ""
			}
		},
		{
			"path": "pages/analysis/analysis",
			"style": {
				"navigationBarTitleText": ""
			}
		},
		{
			"path": "pages/input/input",
			"style": {
				"navigationBarTitleText": ""
			}
		},
		{
			"path": "pages/yearTable/yearTable",
			"style": {
				"navigationBarTitleText": ""
			}
		}
	],
	"globalStyle": {
		"navigationBarTextStyle": "black",
		"navigationBarTitleText": "DataAnalysis",
		"navigationBarBackgroundColor": "#F8F8F8",
		"backgroundColor": "#F8F8F8"
	},
	"uniIdRouter": {}
}